{
    "parent": "minecraft:block_variant/doors/template_door_inventory",
    "textures": {
        "2": "minecraft:textures_variant/doors/dark_oak_door_side",
        "3": "minecraft:block/dark_oak_door_bottom",
        "top": "minecraft:block/dark_oak_door_top"
    },
    "elements": [
        {
            "name": "Box8",
            "from": [0, -7, 6.5],
            "to": [16, 9, 9.5],
            "rotation": {
                "angle": 0,
                "axis": "y",
                "origin": [16, -7, 6.5]
            },
            "faces": {
                "north": {
                    "uv": [0, 0, 16, 16],
                    "texture": "#3"
                },
                "east": {
                    "uv": [3, 0, 6, 16],
                    "texture": "#2"
                },
                "south": {
                    "uv": [0, 0, 16, 16],
                    "texture": "#3"
                },
                "west": {
                    "uv": [6, 0, 3, 16],
                    "texture": "#2"
                },
                "up": {
                    "uv": [6, 0, 9, 16],
                    "rotation": 270,
                    "texture": "#2"
                },
                "down": {
                    "uv": [6, 0, 9, 16],
                    "rotation": 90,
                    "texture": "#2"
                }
            }
        },
        {
            "name": "Box8",
            "from": [0, 9, 6.5],
            "to": [16, 25, 9.5],
            "rotation": {
                "angle": 0,
                "axis": "y",
                "origin": [16, 9, 6.5]
            },
            "faces": {
                "north": {
                    "uv": [0, 0, 16, 16],
                    "texture": "#top"
                },
                "east": {
                    "uv": [0, 0, 3, 16],
                    "texture": "#2"
                },
                "south": {
                    "uv": [0, 0, 16, 16],
                    "texture": "#top"
                },
                "west": {
                    "uv": [3, 0, 0, 16],
                    "texture": "#2"
                },
                "up": {
                    "uv": [6, 0, 9, 16],
                    "rotation": 270,
                    "texture": "#2"
                },
                "down": {
                    "uv": [6, 0, 9, 16],
                    "rotation": 90,
                    "texture": "#2"
                }
            }
        }
    ]
}
