{
	"parent": "minecraft:item_variant/spawn_egg/display_spawn_egg",
	"display": {
		"gui": {
			"rotation": [ 30, 225, 0 ],
			"translation": [ 0, 0, 0],
			"scale":[ 0.7, 0.7, 0.7 ]
		},
		"thirdperson_righthand": {
			"rotation": [90, 0, 0],
			"translation": [0, 0, 0],
			"scale":[ 0.35, 0.35, 0.35 ]
		},
		"thirdperson_lefthand": {
			"rotation": [90, 0, 0],
			"translation": [0, 0, 0],
			"scale":[ 0.35, 0.35, 0.35 ]
		},
		"firstperson_righthand": {
			"rotation": [ 0, 135, 0 ],
			"translation": [ 0, 2, 0 ],
			"scale":[ 0.35, 0.35, 0.35 ]
		},
		"firstperson_lefthand": {
			"rotation": [ 0, 135, 0 ],
			"translation": [ 0, 2, 0 ],
			"scale":[ 0.35, 0.35, 0.35 ]
		},
		"fixed": {
			"rotation": [0, 90, 0],
			"translation": [0, 0, 0],
			"scale":[ 0.7, 0.7, 0.7 ]
		},
		"ground": {
			"rotation": [0, 0, 0],
			"translation": [0, 0, 0],
			"scale":[ 0.7, 0.7, 0.7 ]
		}
	}
}