{
    "parent": "block/block",
    "ambientocclusion": false,
    "textures": {
        "full": "entity/armorstand/wood"
    },
    "elements": [
        {
            "from": [3.5,-4,3.5],
            "to": [12.5,-3.25,12.5],
            "faces": {
                "up": { "uv": [3,8,6,11], "texture": "#full" },
                "down": { "uv": [6,8,9,11], "texture": "#full" },
                "west": { "uv": [3,11,6,11.25], "texture": "#full" },
                "east": { "uv": [3,11,6,11.25], "texture": "#full" },
                "north": { "uv": [3,11,6,11.25], "texture": "#full" },
                "south": { "uv": [3,11,6,11.25], "texture": "#full" }
            }
        },
        {
            "from": [5.75,-3.25,7.25],
            "to": [7.25,5.75,8.75],
            "faces": {
                "west": { "uv": [11,4.5,11.5,7.25], "texture": "#full" },
                "east": { "uv": [11,4.5,11.5,7.25], "texture": "#full" },
                "north": { "uv": [10.5,4.5,11,7.25], "texture": "#full" },
                "south": { "uv": [10.5,4.5,11,7.25], "texture": "#full" }
            }
        },
        {
            "from": [5,5.75,7.25],
            "to": [11,7.25,8.75],
            "faces": {
                "up": { "uv": [0.5,12,2.5,12.5], "texture": "#full" },
                "down": { "uv": [0.5,12,2.5,12.5], "texture": "#full" },
                "west": { "uv": [2.5,12.5,3,13], "texture": "#full" },
                "east": { "uv": [0,12.5,0.5,13], "texture": "#full" },
                "north": { "uv": [0.5,12.5,2.5,13], "texture": "#full" },
                "south": { "uv": [3,12.5,5,13], "texture": "#full" }
            }
        },
        {
            "from": [3.5,12.5,7],
            "to": [12.5,14.75,9.25],
            "faces": {
                "up": { "uv": [0.75,6.5,3.75,7.25], "texture": "#full" },
                "down": { "uv": [3.75,6.5,6.75,7.25], "texture": "#full" },
                "west": { "uv": [3.75,7.25,4.5,8], "texture": "#full" },
                "east": { "uv": [0,7.25,0.75,8], "texture": "#full" },
                "north": { "uv": [0.75,7.25,3.75,8], "texture": "#full" },
                "south": { "uv": [4.5,7.25,7.5,8], "texture": "#full" }
            }
        },
        {
            "from": [7.25,14.75,7.25],
            "to": [8.75,20,8.75],
            "faces": {
                "up": { "uv": [0.5,0,1,0.5], "texture": "#full" },
                "west": { "uv": [0,0.5,0.5,2.25], "texture": "#full" },
                "east": { "uv": [0,0.5,0.5,2.25], "texture": "#full" },
                "north": { "uv": [0.5,0.5,1,2.25], "texture": "#full" },
                "south": { "uv": [0.5,0.5,1,2.25], "texture": "#full" }
            }
        },
        {
            "from": [5.75,7.25,7.25],
            "to": [7.25,12.5,8.75],
            "faces": {
                "west": { "uv": [12,4.5,12.5,6.25], "texture": "#full" },
                "east": { "uv": [12,4.5,12.5,6.25], "texture": "#full" },
                "north": { "uv": [12.5,4.5,13,6.25], "texture": "#full" },
                "south": { "uv": [12.5,4.5,13,6.25], "texture": "#full" }
            }
        },
        {
            "from": [8.75,7.25,7.25],
            "to": [10.25,12.5,8.75],
            "faces": {
                "west": { "uv": [12,4.5,12.5,6.25], "texture": "#full" },
                "east": { "uv": [12,4.5,12.5,6.25], "texture": "#full" },
                "north": { "uv": [12.5,4.5,13,6.25], "texture": "#full" },
                "south": { "uv": [12.5,4.5,13,6.25], "texture": "#full" }
            }
        },
        {
            "from": [8.75,-3.25,7.25],
            "to": [10.25,5.75,8.75],
            "faces": {
                "west": { "uv": [11,4.5,11.5,7.25], "texture": "#full" },
                "east": { "uv": [11,4.5,11.5,7.25], "texture": "#full" },
                "north": { "uv": [10.5,4.5,11,7.25], "texture": "#full" },
                "south": { "uv": [10.5,4.5,11,7.25], "texture": "#full" }
            }
        }
    ]
}