{
    "variants": {
        "": [
            {
                "model": "minecraft:block/dirt"
            },
            {
                "model": "minecraft:block_variant/dirt/dirt1"
            },
            {
                "model": "minecraft:block_variant/dirt/dirt2"
            },
            {
                "model": "minecraft:block_variant/dirt/dirt3"
            },
            {
                "model": "minecraft:block_variant/dirt/dirt4"
            },
            {
                "model": "minecraft:block_variant/dirt/dirt5"
            },
            {
                "model": "minecraft:block_variant/dirt/dirt6"
            },
            {
                "model": "minecraft:block_variant/dirt/dirt7"
            },
            {
                "model": "minecraft:block_variant/dirt/dirt8"
            },
            {
                "model": "minecraft:block_variant/dirt/dirt9"
            }
        ]
    }
}
